README.md
setup.py
pexels_api_py.egg-info/PKG-INFO
pexels_api_py.egg-info/SOURCES.txt
pexels_api_py.egg-info/dependency_links.txt
pexels_api_py.egg-info/requires.txt
pexels_api_py.egg-info/top_level.txt
pexelsapi/__init__.py
pexelsapi/pexels.py
tests/__init__.py
tests/test_pexels.py